pystitch/__init__.py
pystitch/client.py
pystitch/version.py
pystitchconnect-0.0.5.dist-info/LICENSE
pystitchconnect-0.0.5.dist-info/METADATA
pystitchconnect-0.0.5.dist-info/WHEEL
pystitchconnect-0.0.5.dist-info/top_level.txt
pystitchconnect-0.0.5.dist-info/RECORD
