Metadata-Version: 2.1
Name: pystitchconnect
Version: 0.0.5
Summary: Python SDK for Stitch Connect API.
Home-page: https://github.com/dwallace0723/pystitch
Author: David Wallace
Author-email: dwallace0723@gmail.com
License: MIT
Keywords: stitch
Platform: UNKNOWN
Classifier: Intended Audience :: Developers
Classifier: License :: OSI Approved :: MIT License
Classifier: Programming Language :: Python
Classifier: Programming Language :: Python :: 3
Classifier: Programming Language :: Python :: 3.6
Classifier: Programming Language :: Python :: 3.7
Requires-Python: >=3.6
Requires-Dist: requests (>=2.22.0)
Requires-Dist: pytz (==2019.2)
